decoratorfunc.py
decoratorfunc-1.0.dist-info/licenses/LICENSE
decoratorfunc-1.0.dist-info/METADATA
decoratorfunc-1.0.dist-info/WHEEL
decoratorfunc-1.0.dist-info/top_level.txt
decoratorfunc-1.0.dist-info/RECORD
