Metadata-Version: 2.4
Name: decoratorfunc
Version: 1.0
Summary: Simple tools for creating and managing decorator functions in Python.
Author-email: TahsinCr <TahsinCr@outlook.com>
License: MIT
Project-URL: Homepage, https://github.com/TahsinCr/python-decoratorfunc
Project-URL: Source, https://github.com/TahsinCr/python-decoratorfunc
Keywords: decoratorfunc,decorator,definator,func,xcollection
Classifier: Typing :: Typed
Classifier: Intended Audience :: Developers
Classifier: Programming Language :: Python :: 3
Classifier: License :: OSI Approved :: MIT License
Classifier: Operating System :: OS Independent
Requires-Python: >=3
License-File: LICENSE
Requires-Dist: decoratorbasic>=1.0
Dynamic: license-file
